python_packaging_mrm/__init__.py
python_packaging_mrm/maths.py
python_packaging_mrm-0.2.13.dist-info/LICENSE
python_packaging_mrm-0.2.13.dist-info/METADATA
python_packaging_mrm-0.2.13.dist-info/WHEEL
python_packaging_mrm-0.2.13.dist-info/top_level.txt
python_packaging_mrm-0.2.13.dist-info/RECORD
