Metadata-Version: 2.1
Name: python-packaging-mrm
Version: 0.2.13
Summary: Example of how to package Python projects
Author-email: Marta Maciel <marta_maciel@live.com.pt>
License: BSD-3-Clause
Requires-Python: >=3.8.0
License-File: LICENSE
Requires-Dist: numpy
Requires-Dist: pandas
Provides-Extra: dev
Requires-Dist: pytest ; extra == 'dev'
Requires-Dist: setuptools-scm ; extra == 'dev'
Requires-Dist: flake8 ; extra == 'dev'
Requires-Dist: black ; extra == 'dev'
Requires-Dist: pre-commit ; extra == 'dev'
